setup.py
asdb/__init__.py
asdb.egg-info/PKG-INFO
asdb.egg-info/SOURCES.txt
asdb.egg-info/dependency_links.txt
asdb.egg-info/not-zip-safe
asdb.egg-info/pbr.json
asdb.egg-info/requires.txt
asdb.egg-info/top_level.txt
bin/asdb