Metadata-Version: 1.0
Name: asdb
Version: 0.2.8
Summary: Instant convenient debugger
Home-page: https://github.com/alexmojaki/asdb
Author: Alex Hall
Author-email: alex.mojaki@gmail.com
License: MIT
Platform: UNKNOWN
